[
  {
    "pk": 1, 
    "model": "scorecard_processor.scorecard", 
    "fields": {
      "project": 1, 
      "name": "Indicators"
    }
  }, 
  {
    "pk": 1, 
    "model": "scorecard_processor.operation", 
    "fields": {
      "indicator": true, 
      "configuration": "", 
      "description": "2DPa", 
      "scorecard": 1, 
      "operation": "one_minus_num_denom", 
      "identifier": "2DPa"
    }
  }, 
  {
    "pk": 2, 
    "model": "scorecard_processor.operation", 
    "fields": {
      "indicator": true, 
      "configuration": "", 
      "description": "3DP", 
      "scorecard": 1, 
      "operation": "num_denom", 
      "identifier": "3DP"
    }
  }, 
  {
    "pk": 3, 
    "model": "scorecard_processor.operation", 
    "fields": {
      "indicator": true, 
      "configuration": "", 
      "description": "4DP", 
      "scorecard": 1, 
      "operation": "num_denom", 
      "identifier": "4DP"
    }
  }, 
  {
    "pk": 4, 
    "model": "scorecard_processor.operation", 
    "fields": {
      "indicator": true, 
      "configuration": "", 
      "description": "5DPa", 
      "scorecard": 1, 
      "operation": "one_minus_num_denom", 
      "identifier": "5DPa"
    }
  }, 
  {
    "pk": 5, 
    "model": "scorecard_processor.operation", 
    "fields": {
      "indicator": true, 
      "configuration": "", 
      "description": "5DPb", 
      "scorecard": 1, 
      "operation": "one_minus_num_denom", 
      "identifier": "5DPb"
    }
  }, 
  {
    "pk": 6, 
    "model": "scorecard_processor.operation", 
    "fields": {
      "indicator": true, 
      "configuration": "", 
      "description": "5DPc", 
      "scorecard": 1, 
      "operation": "sum_items", 
      "identifier": "5DPc"
    }
  }, 
  {
    "pk": 1, 
    "model": "scorecard_processor.operationargument", 
    "fields": {
      "instance_id": 2, 
      "position": 0, 
      "operation": 1, 
      "instance_content_type": 21, 
      "argument_extractor": "value"
    }
  }, 
  {
    "pk": 3, 
    "model": "scorecard_processor.operationargument", 
    "fields": {
      "instance_id": 5, 
      "position": 0, 
      "operation": 2, 
      "instance_content_type": 21, 
      "argument_extractor": "value"
    }
  }, 
  {
    "pk": 5, 
    "model": "scorecard_processor.operationargument", 
    "fields": {
      "instance_id": 7, 
      "position": 0, 
      "operation": 3, 
      "instance_content_type": 21, 
      "argument_extractor": "value"
    }
  }, 
  {
    "pk": 7, 
    "model": "scorecard_processor.operationargument", 
    "fields": {
      "instance_id": 10, 
      "position": 0, 
      "operation": 4, 
      "instance_content_type": 21, 
      "argument_extractor": "value"
    }
  }, 
  {
    "pk": 9, 
    "model": "scorecard_processor.operationargument", 
    "fields": {
      "instance_id": 12, 
      "position": 0, 
      "operation": 5, 
      "instance_content_type": 21, 
      "argument_extractor": "value"
    }
  }, 
  {
    "pk": 11, 
    "model": "scorecard_processor.operationargument", 
    "fields": {
      "instance_id": 14, 
      "position": 0, 
      "operation": 6, 
      "instance_content_type": 21, 
      "argument_extractor": "value"
    }
  }, 
  {
    "pk": 2, 
    "model": "scorecard_processor.operationargument", 
    "fields": {
      "instance_id": 1, 
      "position": 1, 
      "operation": 1, 
      "instance_content_type": 21, 
      "argument_extractor": "value"
    }
  }, 
  {
    "pk": 4, 
    "model": "scorecard_processor.operationargument", 
    "fields": {
      "instance_id": 4, 
      "position": 1, 
      "operation": 2, 
      "instance_content_type": 21, 
      "argument_extractor": "value"
    }
  }, 
  {
    "pk": 6, 
    "model": "scorecard_processor.operationargument", 
    "fields": {
      "instance_id": 4, 
      "position": 1, 
      "operation": 3, 
      "instance_content_type": 21, 
      "argument_extractor": "value"
    }
  }, 
  {
    "pk": 8, 
    "model": "scorecard_processor.operationargument", 
    "fields": {
      "instance_id": 9, 
      "position": 1, 
      "operation": 4, 
      "instance_content_type": 21, 
      "argument_extractor": "value"
    }
  }, 
  {
    "pk": 10, 
    "model": "scorecard_processor.operationargument", 
    "fields": {
      "instance_id": 1, 
      "position": 1, 
      "operation": 5, 
      "instance_content_type": 21, 
      "argument_extractor": "value"
    }
  }, 
  {
    "pk": 1, 
    "model": "scorecard_processor.reportrun", 
    "fields": {
      "aggregate_on": null, 
      "name": "Mozambique agencies", 
      "compare_series": "Data collection year", 
      "limit_to_entity": [], 
      "limit_to_entitytype": [], 
      "aggregate_by_entity": true, 
      "scorecard": 1, 
      "limit_to_dataseries": [
        1
      ], 
      "description": ""
    }
  }
]