[{"pk": 1, "model": "scorecard_processor.project", "fields": {"name": "IHP example"}}, {"pk": 2, "model": "scorecard_processor.dataseries", "fields": {"project": 1, "group": "year", "name": "2011"}}, {"pk": 5, "model": "scorecard_processor.dataseries", "fields": {"project": 1, "group": "year", "name": "2010"}}, {"pk": 1, "model": "scorecard_processor.dataseries", "fields": {"project": 1, "group": "country", "name": "South Africa"}}, {"pk": 4, "model": "scorecard_processor.dataseries", "fields": {"project": 1, "group": "country", "name": "Somalia"}}, {"pk": 3, "model": "scorecard_processor.dataseries", "fields": {"project": 1, "group": "country", "name": "Nigeria"}}, {"pk": 1, "model": "scorecard_processor.entity", "fields": {"project": 1, "name": "Example Health Org (EHO)"}}, {"pk": 2, "model": "scorecard_processor.entity", "fields": {"project": 1, "name": "Another Health NGO (AHN)"}}, {"pk": 1, "model": "scorecard_processor.survey", "fields": {"project": 1, "data_series": [2, 1], "name": "IHP Survey"}}, {"pk": 1, "model": "scorecard_processor.question", "fields": {"widget": "text", "question": "Aid given ($m)", "validator": "anything", "survey": 1, "help_text": "How much aid did you give?", "identifier": "1"}}, {"pk": 2, "model": "scorecard_processor.question", "fields": {"widget": "text", "question": "Aid budget ($m)", "validator": "anything", "survey": 1, "help_text": "How much aid did you have available?", "identifier": "2"}}, {"pk": 1, "model": "scorecard_processor.scorecard", "fields": {"project": 1, "survey": 1, "name": "Example scorecard"}}, {"pk": 1, "model": "scorecard_processor.indicator", "fields": {"scorecard": 1, "operation": "num_denom", "identifier": "Aid given"}}, {"pk": 1, "model": "scorecard_processor.operationargument", "fields": {"instance_id": 1, "position": 1, "operation": 1, "instance_content_type": 13, "argument_extractor": "value"}}, {"pk": 2, "model": "scorecard_processor.operationargument", "fields": {"instance_id": 2, "position": 2, "operation": 1, "instance_content_type": 13, "argument_extractor": "value"}}]
